{
    "name": "scene",
    "objects": [
        {
            "type": "LIGHT",
            "name": "Light",
            "transform": {
                "translation": [
                    4.076245307922363,
                    1.0054539442062378,
                    5.903861999511719
                ],
                "rotation": [
                    37.261043548583984,
                    3.1637072563171387,
                    106.93630981445312
                ],
                "scaling": [
                    1.0,
                    0.9999999403953552,
                    1.0
                ]
            }
        },
        {
            "type": "CAMERA",
            "name": "Camera",
            "transform": {
                "translation": [
                    7.358891487121582,
                    -6.925790786743164,
                    4.958309173583984
                ],
                "rotation": [
                    63.559303283691406,
                    -2.664711473698844e-06,
                    46.69194793701172
                ],
                "scaling": [
                    1.0,
                    1.0,
                    1.0
                ]
            }
        },
        {
            "type": "MESH",
            "name": "Skydome",
            "transform": {
                "translation": [
                    0.0,
                    0.0,
                    0.0
                ],
                "rotation": [
                    0.0,
                    -0.0,
                    0.0
                ],
                "scaling": [
                    3.184230089187622,
                    8.763559341430664,
                    3.6212449073791504
                ]
            },
            "file_name": "skydome"
        },
        {
            "type": "MESH",
            "name": "Player",
            "transform": {
                "translation": [
                    60.0,
                    0.0,
                    0.0
                ],
                "rotation": [
                    0.0,
                    -0.0,
                    0.0
                ],
                "scaling": [
                    1.0,
                    1.0,
                    1.0
                ]
            },
            "file_name": "player",
            "objecttype": "PLAYER"
        },
        {
            "type": "MESH",
            "name": "boss1",
            "transform": {
                "translation": [
                    -150.0,
                    30.0,
                    10.0
                ],
                "rotation": [
                    0.0,
                    -0.0,
                    0.0
                ],
                "scaling": [
                    3.0,
                    3.0,
                    3.0
                ]
            },
            "file_name": "boss1",
            "objecttype": "ENEMY",
            "objectpattern": "BOSS1"
        },
        {
            "type": "MESH",
            "name": "fallsphere",
            "transform": {
                "translation": [
                    60.0,
                    -25.0,
                    -10.0
                ],
                "rotation": [
                    89.99999237060547,
                    -0.0,
                    0.0
                ],
                "scaling": [
                    10.0,
                    10.0,
                    10.0
                ]
            },
            "file_name": "sphere2",
            "objecttype": "GIMMICK",
            "objectpattern": "FALLSPHERERETURN"
        },
        {
            "type": "MESH",
            "name": "fallsphere.001",
            "transform": {
                "translation": [
                    60.0,
                    0.0,
                    -10.0
                ],
                "rotation": [
                    89.99999237060547,
                    -0.0,
                    0.0
                ],
                "scaling": [
                    10.0,
                    10.0,
                    10.0
                ]
            },
            "file_name": "sphere2",
            "objecttype": "GIMMICK",
            "objectpattern": "FALLSPHERE"
        },
        {
            "type": "MESH",
            "name": "fallsphere.002",
            "transform": {
                "translation": [
                    60.0,
                    25.0,
                    -10.0
                ],
                "rotation": [
                    89.99999237060547,
                    -0.0,
                    0.0
                ],
                "scaling": [
                    10.0,
                    10.0,
                    10.0
                ]
            },
            "file_name": "sphere2",
            "objecttype": "GIMMICK",
            "objectpattern": "FALLSPHERERETURN"
        },
        {
            "type": "MESH",
            "name": "Cube.001",
            "transform": {
                "translation": [
                    -30.0,
                    0.0,
                    0.0
                ],
                "rotation": [
                    0.0,
                    0.0,
                    -90.00000762939453
                ],
                "scaling": [
                    1.0,
                    1.0,
                    1.0
                ]
            },
            "file_name": "enemy1",
            "objecttype": "ENEMY",
            "objectpattern": "ENEMY1"
        },
        {
            "type": "MESH",
            "name": "Cube.002",
            "transform": {
                "translation": [
                    -20.0,
                    0.0,
                    0.0
                ],
                "rotation": [
                    0.0,
                    0.0,
                    -90.00000762939453
                ],
                "scaling": [
                    1.0,
                    1.0,
                    1.0
                ]
            },
            "file_name": "enemy1",
            "objecttype": "ENEMY",
            "objectpattern": "ENEMY2"
        },
        {
            "type": "MESH",
            "name": "Cube.003",
            "transform": {
                "translation": [
                    -10.0,
                    0.0,
                    0.0
                ],
                "rotation": [
                    0.0,
                    0.0,
                    -90.00000762939453
                ],
                "scaling": [
                    1.0,
                    1.0,
                    1.0
                ]
            },
            "file_name": "enemy1",
            "objecttype": "ENEMY",
            "objectpattern": "ENEMY1"
        },
        {
            "type": "MESH",
            "name": "球.001",
            "transform": {
                "translation": [
                    135.0,
                    0.0,
                    0.0
                ],
                "rotation": [
                    0.0,
                    -0.0,
                    0.0
                ],
                "scaling": [
                    50.0,
                    50.0,
                    50.0
                ]
            },
            "file_name": "earth",
            "objecttype": "EARTH"
        },
        {
            "type": "MESH",
            "name": "Cube.004",
            "transform": {
                "translation": [
                    -10.0,
                    25.0,
                    0.0
                ],
                "rotation": [
                    0.0,
                    0.0,
                    -90.00000762939453
                ],
                "scaling": [
                    1.0,
                    1.0,
                    1.0
                ]
            },
            "file_name": "enemy1",
            "objecttype": "ENEMY",
            "objectpattern": "ENEMY1"
        },
        {
            "type": "MESH",
            "name": "Cube.005",
            "transform": {
                "translation": [
                    -10.0,
                    -25.0,
                    0.0
                ],
                "rotation": [
                    0.0,
                    0.0,
                    -90.00000762939453
                ],
                "scaling": [
                    1.0,
                    1.0,
                    1.0
                ]
            },
            "file_name": "enemy1",
            "objecttype": "ENEMY",
            "objectpattern": "ENEMY1"
        },
        {
            "type": "MESH",
            "name": "Cube.006",
            "transform": {
                "translation": [
                    -60.0,
                    0.0,
                    0.0
                ],
                "rotation": [
                    0.0,
                    0.0,
                    -90.00000762939453
                ],
                "scaling": [
                    1.0,
                    1.0,
                    1.0
                ]
            },
            "file_name": "enemy1",
            "objecttype": "ENEMY",
            "objectpattern": "ENEMY2"
        },
        {
            "type": "MESH",
            "name": "Cube.007",
            "transform": {
                "translation": [
                    -40.0,
                    25.0,
                    0.0
                ],
                "rotation": [
                    0.0,
                    0.0,
                    -90.00000762939453
                ],
                "scaling": [
                    1.0,
                    1.0,
                    1.0
                ]
            },
            "file_name": "enemy1",
            "objecttype": "ENEMY",
            "objectpattern": "ENEMY1"
        },
        {
            "type": "MESH",
            "name": "Cube.008",
            "transform": {
                "translation": [
                    -40.0,
                    -25.0,
                    0.0
                ],
                "rotation": [
                    0.0,
                    0.0,
                    -90.00000762939453
                ],
                "scaling": [
                    1.0,
                    1.0,
                    1.0
                ]
            },
            "file_name": "enemy1",
            "objecttype": "ENEMY",
            "objectpattern": "ENEMY1"
        },
        {
            "type": "MESH",
            "name": "Cube.009",
            "transform": {
                "translation": [
                    -50.0,
                    25.0,
                    0.0
                ],
                "rotation": [
                    0.0,
                    0.0,
                    -53.130104064941406
                ],
                "scaling": [
                    0.0,
                    1.0,
                    1.0
                ]
            },
            "file_name": "enemy1",
            "objecttype": "ENEMY",
            "objectpattern": "ENEMY1"
        },
        {
            "type": "MESH",
            "name": "Cube.010",
            "transform": {
                "translation": [
                    -50.0,
                    -25.50890350341797,
                    0.0
                ],
                "rotation": [
                    0.0,
                    0.0,
                    -90.00000762939453
                ],
                "scaling": [
                    1.0,
                    1.0,
                    1.0
                ]
            },
            "file_name": "enemy1",
            "objecttype": "ENEMY",
            "objectpattern": "ENEMY1"
        },
        {
            "type": "MESH",
            "name": "Cube.011",
            "transform": {
                "translation": [
                    -70.0,
                    0.0,
                    0.0
                ],
                "rotation": [
                    0.0,
                    0.0,
                    -90.00000762939453
                ],
                "scaling": [
                    1.0,
                    1.0,
                    1.0
                ]
            },
            "file_name": "enemy1",
            "objecttype": "ENEMY",
            "objectpattern": "ENEMY1"
        },
        {
            "type": "MESH",
            "name": "Cube.012",
            "transform": {
                "translation": [
                    -80.0,
                    0.0,
                    0.0
                ],
                "rotation": [
                    0.0,
                    0.0,
                    -90.00000762939453
                ],
                "scaling": [
                    1.0,
                    1.0,
                    1.0
                ]
            },
            "file_name": "enemy1",
            "objecttype": "ENEMY",
            "objectpattern": "ENEMY1"
        },
        {
            "type": "MESH",
            "name": "Cube.013",
            "transform": {
                "translation": [
                    -70.0,
                    25.0,
                    0.0
                ],
                "rotation": [
                    0.0,
                    0.0,
                    -90.00000762939453
                ],
                "scaling": [
                    1.0,
                    1.0,
                    1.0
                ]
            },
            "file_name": "enemy1",
            "objecttype": "ENEMY",
            "objectpattern": "ENEMY1"
        },
        {
            "type": "MESH",
            "name": "Cube.014",
            "transform": {
                "translation": [
                    -70.0,
                    -25.50890350341797,
                    0.0
                ],
                "rotation": [
                    0.0,
                    0.0,
                    -90.00000762939453
                ],
                "scaling": [
                    1.0,
                    1.0,
                    1.0
                ]
            },
            "file_name": "enemy1",
            "objecttype": "ENEMY",
            "objectpattern": "ENEMY1"
        },
        {
            "type": "MESH",
            "name": "円柱",
            "transform": {
                "translation": [
                    -8.208085060119629,
                    0.0,
                    0.0
                ],
                "rotation": [
                    90.00000762939453,
                    -0.0,
                    0.0
                ],
                "scaling": [
                    10.0,
                    1.0,
                    1.0
                ]
            },
            "file_name": "rail"
        },
        {
            "type": "MESH",
            "name": "円柱.001",
            "transform": {
                "translation": [
                    -10.0,
                    25.0,
                    0.0
                ],
                "rotation": [
                    90.00000762939453,
                    -0.0,
                    0.0
                ],
                "scaling": [
                    10.0,
                    1.0,
                    1.0
                ]
            },
            "file_name": "rail"
        },
        {
            "type": "MESH",
            "name": "円柱.002",
            "transform": {
                "translation": [
                    -10.0,
                    -25.0,
                    0.0
                ],
                "rotation": [
                    90.00000762939453,
                    -0.0,
                    0.0
                ],
                "scaling": [
                    10.0,
                    1.0,
                    1.0
                ]
            },
            "file_name": "rail"
        }
    ]
}