{
    "name": "scene",
    "objects": [
        {
            "type": "LIGHT",
            "name": "Light",
            "transform": {
                "translation": [
                    4.076245307922363,
                    1.0054539442062378,
                    5.903861999511719
                ],
                "rotation": [
                    37.26104736328125,
                    3.1637091636657715,
                    106.93632507324219
                ],
                "scaling": [
                    1.0,
                    0.9999999403953552,
                    1.0
                ]
            }
        },
        {
            "type": "CAMERA",
            "name": "Camera",
            "transform": {
                "translation": [
                    7.358891487121582,
                    -6.925790786743164,
                    4.958309173583984
                ],
                "rotation": [
                    63.559295654296875,
                    2.2983238068263745e-07,
                    46.69194412231445
                ],
                "scaling": [
                    1.0,
                    1.0,
                    1.0
                ]
            }
        },
        {
            "type": "MESH",
            "name": "Skydome",
            "transform": {
                "translation": [
                    0.0,
                    0.0,
                    0.0
                ],
                "rotation": [
                    0.0,
                    -0.0,
                    0.0
                ],
                "scaling": [
                    7.0,
                    7.0,
                    7.0
                ]
            },
            "file_name": "skydomet",
            "objecttype": "SKYDOME"
        },
        {
            "type": "MESH",
            "name": "Goal",
            "transform": {
                "translation": [
                    0.0,
                    307.5592041015625,
                    0.0
                ],
                "rotation": [
                    0.0,
                    -0.0,
                    0.0
                ],
                "scaling": [
                    10.0,
                    10.0,
                    10.0
                ]
            },
            "file_name": "sphere",
            "objecttype": "GOAL"
        },
        {
            "type": "MESH",
            "name": "Player",
            "transform": {
                "translation": [
                    60.0,
                    -30.0,
                    -8.0
                ],
                "rotation": [
                    0.0,
                    -0.0,
                    -90.00000762939453
                ],
                "scaling": [
                    1.0,
                    1.0,
                    1.0
                ]
            },
            "file_name": "playerdash",
            "objecttype": "PLAYER"
        },
        {
            "type": "MESH",
            "name": "Plane.002",
            "transform": {
                "translation": [
                    15.843988418579102,
                    -10.863222122192383,
                    -10.0
                ],
                "rotation": [
                    0.0,
                    -0.0,
                    0.0
                ],
                "scaling": [
                    0.594528079032898,
                    0.3986983597278595,
                    1.0
                ]
            },
            "file_name": "ground",
            "collider": {
                "type": "BOX",
                "center": [
                    10.0,
                    0.0,
                    0.0
                ],
                "size": [
                    200.0,
                    200.0,
                    2.0
                ]
            }
        },
        {
            "type": "MESH",
            "name": "Cube",
            "transform": {
                "translation": [
                    0.0,
                    25.0,
                    0.0
                ],
                "rotation": [
                    0.0,
                    -0.0,
                    -90.00000762939453
                ],
                "scaling": [
                    1.0,
                    1.0,
                    1.0
                ]
            },
            "file_name": "enemy1",
            "objecttype": "ENEMY",
            "objectpattern": "ENEMY1"
        },
        {
            "type": "MESH",
            "name": "Cube.001",
            "transform": {
                "translation": [
                    0.0,
                    60.0,
                    20.0
                ],
                "rotation": [
                    0.0,
                    -0.0,
                    -90.00000762939453
                ],
                "scaling": [
                    1.0,
                    1.0,
                    1.0
                ]
            },
            "file_name": "enemy1",
            "objecttype": "ENEMY",
            "objectpattern": "E2S"
        },
        {
            "type": "MESH",
            "name": "Plane.001",
            "transform": {
                "translation": [
                    -1.4062175750732422,
                    79.22119140625,
                    -10.0
                ],
                "rotation": [
                    0.0,
                    -0.0,
                    0.0
                ],
                "scaling": [
                    0.1909095048904419,
                    0.3986983597278595,
                    1.0
                ]
            },
            "file_name": "ground",
            "collider": {
                "type": "BOX",
                "center": [
                    10.0,
                    0.0,
                    0.0
                ],
                "size": [
                    200.0,
                    200.0,
                    2.0
                ]
            }
        },
        {
            "type": "MESH",
            "name": "Cube.002",
            "transform": {
                "translation": [
                    0.0,
                    100.0,
                    20.0
                ],
                "rotation": [
                    0.0,
                    -0.0,
                    -90.00000762939453
                ],
                "scaling": [
                    1.0,
                    1.0,
                    1.0
                ]
            },
            "file_name": "enemy1",
            "objecttype": "ENEMY",
            "objectpattern": "ENEMY1"
        },
        {
            "type": "MESH",
            "name": "Plane.003",
            "transform": {
                "translation": [
                    -1.4062175750732422,
                    193.82154846191406,
                    -10.0
                ],
                "rotation": [
                    0.0,
                    -0.0,
                    0.0
                ],
                "scaling": [
                    0.1909095048904419,
                    0.3986983597278595,
                    1.0
                ]
            },
            "file_name": "ground",
            "collider": {
                "type": "BOX",
                "center": [
                    10.0,
                    0.0,
                    0.0
                ],
                "size": [
                    200.0,
                    200.0,
                    2.0
                ]
            }
        },
        {
            "type": "MESH",
            "name": "Plane.004",
            "transform": {
                "translation": [
                    55.806976318359375,
                    176.15016174316406,
                    -10.0
                ],
                "rotation": [
                    0.0,
                    -0.0,
                    0.0
                ],
                "scaling": [
                    0.1909095048904419,
                    0.9622400999069214,
                    1.0
                ]
            },
            "file_name": "ground",
            "collider": {
                "type": "BOX",
                "center": [
                    10.0,
                    0.0,
                    0.0
                ],
                "size": [
                    200.0,
                    200.0,
                    2.0
                ]
            }
        },
        {
            "type": "MESH",
            "name": "Plane.005",
            "transform": {
                "translation": [
                    21.019054412841797,
                    307.21142578125,
                    -10.0
                ],
                "rotation": [
                    0.0,
                    -0.0,
                    0.0
                ],
                "scaling": [
                    0.5124586224555969,
                    0.17784593999385834,
                    1.0
                ]
            },
            "file_name": "ground",
            "collider": {
                "type": "BOX",
                "center": [
                    10.0,
                    0.0,
                    0.0
                ],
                "size": [
                    200.0,
                    200.0,
                    2.0
                ]
            }
        },
        {
            "type": "MESH",
            "name": "Cube.003",
            "transform": {
                "translation": [
                    60.0,
                    225.0,
                    10.0
                ],
                "rotation": [
                    0.0,
                    -0.0,
                    -90.00000762939453
                ],
                "scaling": [
                    1.0,
                    1.0,
                    1.0
                ]
            },
            "file_name": "enemy1",
            "objecttype": "ENEMY",
            "objectpattern": "ENEMY2"
        },
        {
            "type": "MESH",
            "name": "Cube.004",
            "transform": {
                "translation": [
                    60.0,
                    260.0,
                    0.0
                ],
                "rotation": [
                    0.0,
                    -0.0,
                    -90.00000762939453
                ],
                "scaling": [
                    1.0,
                    1.0,
                    1.0
                ]
            },
            "file_name": "enemy1",
            "objecttype": "ENEMY",
            "objectpattern": "E1P"
        },
        {
            "type": "MESH",
            "name": "Cube.005",
            "transform": {
                "translation": [
                    0.0,
                    200.0,
                    40.0
                ],
                "rotation": [
                    0.0,
                    -0.0,
                    -90.00000762939453
                ],
                "scaling": [
                    1.0,
                    1.0,
                    1.0
                ]
            },
            "file_name": "enemy1",
            "objecttype": "ENEMY",
            "objectpattern": "E2S"
        },
        {
            "type": "MESH",
            "name": "Cube.006",
            "transform": {
                "translation": [
                    60.0,
                    200.0,
                    0.0
                ],
                "rotation": [
                    0.0,
                    -0.0,
                    -90.00000762939453
                ],
                "scaling": [
                    1.0,
                    1.0,
                    1.0
                ]
            },
            "file_name": "enemy1",
            "objecttype": "ENEMY",
            "objectpattern": "ENEMY1"
        },
        {
            "type": "MESH",
            "name": "Cube.007",
            "transform": {
                "translation": [
                    0.0,
                    225.0,
                    40.0
                ],
                "rotation": [
                    0.0,
                    -0.0,
                    -90.00000762939453
                ],
                "scaling": [
                    1.0,
                    1.0,
                    1.0
                ]
            },
            "file_name": "enemy1",
            "objecttype": "ENEMY",
            "objectpattern": "E2S"
        },
        {
            "type": "MESH",
            "name": "Cube.008",
            "transform": {
                "translation": [
                    60.0,
                    320.0,
                    20.0
                ],
                "rotation": [
                    0.0,
                    -0.0,
                    -90.00000762939453
                ],
                "scaling": [
                    1.0,
                    1.0,
                    1.0
                ]
            },
            "file_name": "enemy1",
            "objecttype": "ENEMY",
            "objectpattern": "ENEMY2"
        }
    ]
}